csvnorm/__init__.py
csvnorm/__main__.py
csvnorm/cli.py
csvnorm/core.py
csvnorm/encoding.py
csvnorm/mojibake.py
csvnorm/ui.py
csvnorm/utils.py
csvnorm/validation.py
csvnorm-1.2.8.dist-info/licenses/LICENSE
csvnorm-1.2.8.dist-info/METADATA
csvnorm-1.2.8.dist-info/WHEEL
csvnorm-1.2.8.dist-info/entry_points.txt
csvnorm-1.2.8.dist-info/top_level.txt
csvnorm-1.2.8.dist-info/RECORD
