Metadata-Version: 2.4
Name: csvnorm
Version: 1.2.8
Summary: A command-line utility to validate and normalize CSV files
Author-email: aborruso <aborruso@gmail.com>
License: MIT License
Project-URL: Homepage, https://github.com/aborruso/prepare_data
Project-URL: Issues, https://github.com/aborruso/prepare_data/issues
Keywords: csv,data,normalization,validation,etl
Classifier: Development Status :: 5 - Production/Stable
Classifier: Intended Audience :: Developers
Classifier: Intended Audience :: Science/Research
Classifier: License :: OSI Approved :: MIT License
Classifier: Operating System :: OS Independent
Classifier: Programming Language :: Python :: 3
Classifier: Programming Language :: Python :: 3.9
Classifier: Programming Language :: Python :: 3.10
Classifier: Programming Language :: Python :: 3.11
Classifier: Programming Language :: Python :: 3.12
Classifier: Topic :: Scientific/Engineering :: Information Analysis
Classifier: Topic :: Software Development :: Libraries
Classifier: Topic :: Utilities
Requires-Python: >=3.9
License-File: LICENSE
Requires-Dist: charset-normalizer>=3.0.0
Requires-Dist: duckdb>=0.9.0
Requires-Dist: ftfy>=6.3.1
Requires-Dist: requests>=2.31.0
Requires-Dist: rich>=13.0.0
Requires-Dist: rich-argparse>=1.0.0
Provides-Extra: dev
Requires-Dist: pytest>=7.0.0; extra == "dev"
Requires-Dist: pytest-cov>=4.0.0; extra == "dev"
Requires-Dist: ruff>=0.1.0; extra == "dev"
Requires-Dist: mypy>=1.8.0; extra == "dev"
Requires-Dist: types-requests>=2.31.0; extra == "dev"
Dynamic: license-file
